scriv/__init__.py
scriv/__main__.py
scriv/changelog.py
scriv/cli.py
scriv/collect.py
scriv/config.py
scriv/create.py
scriv/exceptions.py
scriv/format.py
scriv/format_md.py
scriv/format_rst.py
scriv/ghrel.py
scriv/github.py
scriv/gitinfo.py
scriv/linkcheck.py
scriv/literals.py
scriv/optional.py
scriv/print.py
scriv/scriv.py
scriv/shell.py
scriv/util.py
scriv/templates/new_fragment.md.j2
scriv/templates/new_fragment.rst.j2
scriv-1.8.0.dist-info/licenses/LICENSE.txt
scriv-1.8.0.dist-info/METADATA
scriv-1.8.0.dist-info/WHEEL
scriv-1.8.0.dist-info/entry_points.txt
scriv-1.8.0.dist-info/top_level.txt
scriv-1.8.0.dist-info/RECORD
