Metadata-Version: 2.4
Name: scriv
Version: 1.8.0
Summary: Scriv changelog management tool
Author-email: Ned Batchelder <ned@nedbatchelder.com>
License-Expression: Apache-2.0
Project-URL: Mastodon, https://hachyderm.io/@nedbat
Project-URL: Funding, https://github.com/sponsors/nedbat
Project-URL: Issues, https://github.com/nedbat/scriv/issues
Project-URL: Source, https://github.com/nedbat/scriv
Project-URL: Home, https://github.com/nedbat/scriv
Project-URL: Documentation, https://scriv.readthedocs.io
Classifier: Development Status :: 5 - Production/Stable
Classifier: Intended Audience :: Developers
Classifier: Programming Language :: Python
Classifier: Programming Language :: Python :: 3
Classifier: Programming Language :: Python :: 3.10
Classifier: Programming Language :: Python :: 3.11
Classifier: Programming Language :: Python :: 3.12
Classifier: Programming Language :: Python :: 3.13
Classifier: Programming Language :: Python :: 3.14
Requires-Python: >=3.10
License-File: LICENSE.txt
Requires-Dist: attrs
Requires-Dist: click
Requires-Dist: click-log
Requires-Dist: jinja2>=2.7
Requires-Dist: markdown-it-py
Requires-Dist: requests
Provides-Extra: toml
Requires-Dist: tomli; python_version < "3.11" and extra == "toml"
Provides-Extra: yaml
Requires-Dist: pyyaml; extra == "yaml"
Dynamic: license-file
